perambulate/__init__.py
perambulate/condition/__init__.py
perambulate/condition/condition.py
perambulate/condition/functions.py
perambulate-0.1.3.dist-info/WHEEL
perambulate-0.1.3.dist-info/METADATA
perambulate-0.1.3.dist-info/RECORD
