Metadata-Version: 2.1
Name: perambulate
Version: 0.1.3
Summary: Timeseries analysis modules
License: MIT
Author: Jordi Dekker
Author-email: pypi@jordidekker.net
Requires-Python: >=3.7,<4.0
Classifier: License :: OSI Approved :: MIT License
Classifier: Programming Language :: Python :: 3
Classifier: Programming Language :: Python :: 3.7
Classifier: Programming Language :: Python :: 3.8
Classifier: Programming Language :: Python :: 3.9
Requires-Dist: matplotlib (>=3.3.4,<4.0.0)
Requires-Dist: numpy
Requires-Dist: pandas (>=1.0.1,<2.0.0)
